actuarialCalculus/Calculations.py
actuarialCalculus/__init__.py
actuarialCalculus-0.0.2.dist-info/LICENSE
actuarialCalculus-0.0.2.dist-info/METADATA
actuarialCalculus-0.0.2.dist-info/WHEEL
actuarialCalculus-0.0.2.dist-info/top_level.txt
actuarialCalculus-0.0.2.dist-info/RECORD
