Metadata-Version: 2.1
Name: actuarialCalculus
Version: 0.0.2
Summary: a library to perform actuarial calculations
Author: Jesus Gomez-Brana Gonzalez
Author-email: jesus.gomezbranago@anahuac.mx
Classifier: Programming Language :: Python :: 3
Classifier: License :: OSI Approved :: MIT License
Classifier: Operating System :: OS Independent
License-File: LICENSE
Requires-Dist: numpy
Requires-Dist: twine
